iromeku/__init__.py
iromeku/iromeku.py
iromeku/main.py
iromeku/py.typed
test/__init__.py
test/test_sanity.py
tests/__init__.py
tests/sanity_tests.py
iromeku-0.0.1.dist-info/LICENSE
iromeku-0.0.1.dist-info/METADATA
iromeku-0.0.1.dist-info/WHEEL
iromeku-0.0.1.dist-info/top_level.txt
iromeku-0.0.1.dist-info/RECORD
